cnnClassifier/__init__.py
cnnClassifier/components/__init__.py
cnnClassifier/components/data_ingestion.py
cnnClassifier/components/model_evaluation_mlflow.py
cnnClassifier/components/model_trainer.py
cnnClassifier/components/prepare_base_model.py
cnnClassifier/config/__init__.py
cnnClassifier/config/configuration.py
cnnClassifier/constants/__init__.py
cnnClassifier/entity/__init__.py
cnnClassifier/entity/config_entity.py
cnnClassifier/pipeline/__init__.py
cnnClassifier/pipeline/prediction.py
cnnClassifier/pipeline/stage_01_data_ingestion.py
cnnClassifier/pipeline/stage_02_prepare_base_model.py
cnnClassifier/pipeline/stage_03_model_trainer.py
cnnClassifier/pipeline/stage_04_model_evaluation.py
cnnClassifier/utils/__init__.py
cnnClassifier/utils/common.py
dog_cat_cnn_classifier-0.1.0.dist-info/LICENSE
dog_cat_cnn_classifier-0.1.0.dist-info/METADATA
dog_cat_cnn_classifier-0.1.0.dist-info/WHEEL
dog_cat_cnn_classifier-0.1.0.dist-info/top_level.txt
dog_cat_cnn_classifier-0.1.0.dist-info/RECORD
