Metadata-Version: 2.2
Name: dog-cat-cnn-classifier
Version: 0.1.0
Summary: A deep learning package for dog and cat image classification using CNN
Home-page: https://github.com/nishantbadhautiya/dog-cat-classifier
Author: nishantbadhautiya
Author-email: nishantbadhautiya100@gmail.com
License: MIT
Project-URL: Bug Tracker, https://github.com/nishantbadhautiya/dog-cat-classifier/issues
Classifier: Programming Language :: Python :: 3
Classifier: License :: OSI Approved :: MIT License
Classifier: Operating System :: OS Independent
Classifier: Intended Audience :: Developers
Classifier: Topic :: Scientific/Engineering :: Artificial Intelligence
Requires-Python: >=3.7
License-File: LICENSE
Requires-Dist: tensorflow>=2.0.0
Requires-Dist: numpy>=1.19.0
Requires-Dist: pandas>=1.2.0
Requires-Dist: scikit-learn>=0.24.0
Requires-Dist: keras>=2.4.0
Requires-Dist: PyYAML>=5.4.0
Dynamic: author
Dynamic: author-email
Dynamic: classifier
Dynamic: description
Dynamic: description-content-type
Dynamic: home-page
Dynamic: license
Dynamic: project-url
Dynamic: requires-dist
Dynamic: requires-python
Dynamic: summary
